{
  "kbId": "bank-redis",
  "topicId": "redis20-4-8-4-8-38081-593-8-585-5-38081-99-86-7-4-58886-588-8-7-3-586-3-4-80-4-988-997-9-298-9",
  "subjectId": "2-68-81-4-985-58-96-4-88-9-98-58-794-8",
  "updatedAt": "2026-05-09",
  "content": {
    "title": "Redis 主从、哨兵、集群分别解决什么问题？",
    "breadcrumb": [
      "Redis题库",
      "持久化与高可用",
      "Redis 主从、哨兵、集群分别解决什么问题？"
    ],
    "quickFacts": [
      {
        "k": "知识点",
        "v": "Redis 主从、哨兵、集群分别解决什么问题？"
      },
      {
        "k": "所属模块",
        "v": "持久化与高可用"
      },
      {
        "k": "题库主题",
        "v": "Redis"
      },
      {
        "k": "难度",
        "v": "中等"
      },
      {
        "k": "面试频率",
        "v": "高频"
      },
      {
        "k": "学习主线",
        "v": "Redis 题想拿高分，必须把“机制 + 场景 + 风险控制”一起讲出来。"
      }
    ],
    "sections": [
      {
        "id": "knowledge-summary",
        "h2": "知识点总结",
        "paragraphs": [
          "Redis 题的主线通常是“为什么快、怎么存、怎么持久化、怎么做高可用、怎么处理缓存问题”。",
          "面试官常常会把数据结构、高可用和缓存一致性串起来连续追问。"
        ],
        "bullets": [
          "Redis 单线程处理命令配合高效 IO 模型，是高性能的重要基础。",
          "不同数据结构适合不同业务模型，例如 String 做缓存、ZSet 做排行榜。",
          "RDB 和 AOF 的取舍本质是性能、恢复速度和数据丢失窗口的取舍。",
          "缓存穿透、击穿、雪崩、一致性是 Redis 最典型的业务落地题。"
        ]
      },
      {
        "id": "interview-highlights",
        "h2": "面试常问",
        "paragraphs": [],
        "bullets": [
          "面试官问「Redis 主从、哨兵、集群分别解决什么问题」时，30 秒内应该先给出什么核心结论？",
          "Redis 主从、哨兵、集群分别解决什么问题背后的关键机制是什么，为什么要这样设计？",
          "Redis 主从、哨兵、集群分别解决什么问题在真实项目里通常怎么用，如何说明场景和取舍？",
          "Redis 主从、哨兵、集群分别解决什么问题最容易踩的坑、风险和边界是什么？",
          "面试官问到「Redis 主从、哨兵、集群分别解决什么问题」时，30 秒内应该先给出什么结论？",
          "如果继续追问原理，应该补充哪些关键机制和边界条件？"
        ],
        "callout": "面试模式下建议先给 30 秒结论，再按原理、边界、项目场景逐层展开。"
      },
      {
        "id": "reference-answer",
        "h2": "参考答案和解析",
        "paragraphs": [
          "30 秒回答：面试官问到「Redis 主从、哨兵、集群分别解决什么问题？」时，先给出核心结论：Redis 题的主线通常是“为什么快、怎么存、怎么持久化、怎么做高可用、怎么处理缓存问题”；面试官常常会把数据结构、高可用和缓存一致性串起来连续追问。",
          "1 分钟回答：然后按“定义和目标 -> 原理机制 -> 场景边界 -> 项目取舍”的顺序展开。Redis 单线程处理命令配合高效 IO 模型，是高性能的重要基础；不同数据结构适合不同业务模型，例如 String 做缓存、ZSet 做排行榜；RDB 和 AOF 的取舍本质是性能、恢复速度和数据丢失窗口的取舍；缓存穿透、击穿、雪崩、一致性是 Redis 最典型的业务落地题。",
          "深入追问：如果面试官继续追问，可以沿着这条主线回答：先围绕当前题目说明 Redis 的核心机制；再讲业务场景、性能收益和风险点；然后说明高可用或一致性治理方法；最后补实际项目里的监控与排障策略。 最后结合项目中的使用、排查或风险控制收口。"
        ],
        "bullets": [
          "先围绕当前题目说明 Redis 的核心机制。",
          "再讲业务场景、性能收益和风险点。",
          "然后说明高可用或一致性治理方法。",
          "最后补实际项目里的监控与排障策略。",
          "项目表达时，要说明这个知识点解决了什么业务或工程问题，以及为什么选择这种方案。",
          "风险和误区要主动补充，例如性能影响、边界条件、线程安全、数据一致性或维护成本。"
        ]
      }
    ],
    "selfTests": [],
    "sources": []
  }
}